crcsolver/__init__.py
crcsolver/bitmatrix.py
crcsolver/crc_catalog.py
crcsolver/main.py
crcsolver/subsetxor.py
crcsolver-1.0.3.dist-info/LICENSE
crcsolver-1.0.3.dist-info/METADATA
crcsolver-1.0.3.dist-info/WHEEL
crcsolver-1.0.3.dist-info/top_level.txt
crcsolver-1.0.3.dist-info/RECORD
