Metadata-Version: 2.1
Name: crcsolver
Version: 1.0.3
Summary: solve for data, given a target crc
Home-page: https://github.com/lwerdna/crcsolver
Author: Andrew Lamoureux
Author-email: foo@bar.com
License: UNKNOWN
Platform: UNKNOWN
Classifier: Programming Language :: Python :: 3
Classifier: License :: Public Domain
Classifier: Operating System :: OS Independent
